LICENSE
MANIFEST.in
README
README.md
setup.cfg
setup.py
pyiArduinoI2Cencoder/__init__.py
pyiArduinoI2Cencoder/iarduino_I2C_Encoder.cpp
pyiArduinoI2Cencoder/iarduino_I2C_Encoder.h
pyiArduinoI2Cencoder/iarduino_I2C_Encoder.pxd
pyiArduinoI2Cencoder/iarduino_I2C_PI.h
pyiArduinoI2Cencoder/pyiArduinoI2Cencoder.cpp
pyiArduinoI2Cencoder/pyiArduinoI2Cencoder.pyx
pyiArduinoI2Cencoder/setup.py
pyiArduinoI2Cencoder.egg-info/PKG-INFO
pyiArduinoI2Cencoder.egg-info/SOURCES.txt
pyiArduinoI2Cencoder.egg-info/dependency_links.txt
pyiArduinoI2Cencoder.egg-info/top_level.txt
pyiArduinoI2Cencoder/cpp/EncTurn.cpp
pyiArduinoI2Cencoder/cpp/EncTurnLeftRight.cpp
pyiArduinoI2Cencoder/cpp/FindDevices.cpp
pyiArduinoI2Cencoder/cpp/KeyChanged.cpp
pyiArduinoI2Cencoder/cpp/KeyHold.cpp
pyiArduinoI2Cencoder/cpp/KeyPressed.cpp
pyiArduinoI2Cencoder/cpp/KeyPushed.cpp
pyiArduinoI2Cencoder/cpp/KeyReleased.cpp
pyiArduinoI2Cencoder/cpp/KeyTimePressed.cpp
pyiArduinoI2Cencoder/cpp/KeyTrigger.cpp
pyiArduinoI2Cencoder/cpp/NewAddress.cpp
pyiArduinoI2Cencoder/cpp/PinModeDAC.cpp
pyiArduinoI2Cencoder/cpp/PinModeFrequency.cpp
pyiArduinoI2Cencoder/cpp/PinModeKey.cpp
pyiArduinoI2Cencoder/cpp/PinModeOff.cpp
pyiArduinoI2Cencoder/cpp/PinModePWM.cpp
pyiArduinoI2Cencoder/cpp/PinModePWMlog.cpp
pyiArduinoI2Cencoder/cpp/PinModeServo.cpp
pyiArduinoI2Cencoder/cpp/PinModeTrigger.cpp
pyiArduinoI2Cencoder/cpp/PositionGet.cpp
pyiArduinoI2Cencoder/cpp/PositionReset.cpp
pyiArduinoI2Cencoder/cpp/PositionSettings.cpp
pyiArduinoI2Cencoder/examples/EncTurn.py
pyiArduinoI2Cencoder/examples/EncTurnLeftRight.py
pyiArduinoI2Cencoder/examples/FindDevices.py
pyiArduinoI2Cencoder/examples/KeyChanged.py
pyiArduinoI2Cencoder/examples/KeyHold.py
pyiArduinoI2Cencoder/examples/KeyPressed.py
pyiArduinoI2Cencoder/examples/KeyPushed.py
pyiArduinoI2Cencoder/examples/KeyReleased.py
pyiArduinoI2Cencoder/examples/KeyTimePressed.py
pyiArduinoI2Cencoder/examples/KeyTrigger.py
pyiArduinoI2Cencoder/examples/PinModeDAC.py
pyiArduinoI2Cencoder/examples/PinModeFrequency.py
pyiArduinoI2Cencoder/examples/PinModeKey.py
pyiArduinoI2Cencoder/examples/PinModeOff.py
pyiArduinoI2Cencoder/examples/PinModePWM.py
